README.md
setup.py
bookrest/__init__.py
bookrest/admin.py
bookrest/apps.py
bookrest/introspect.py
bookrest/models.py
bookrest/tests.py
bookrest/urls.py
bookrest/utils.py
bookrest/views.py
bookrest.egg-info/PKG-INFO
bookrest.egg-info/SOURCES.txt
bookrest.egg-info/dependency_links.txt
bookrest.egg-info/requires.txt
bookrest.egg-info/top_level.txt
bookrest/migrations/__init__.py