Metadata-Version: 2.1
Name: bookrest
Version: 0.1.4
Summary: The easiest way to add a Django and DRF powered API to any project
Home-page: https://www.agiliq.com/apps/bookrest/
Author-email: hello@agiliq.com
License: BSD
Platform: UNKNOWN
